pyanilist/__init__.py
pyanilist/_aclient.py
pyanilist/_client.py
pyanilist/_enums.py
pyanilist/_errors.py
pyanilist/_query.py
pyanilist/_types.py
pyanilist/_utils.py
pyanilist/_version.py
pyanilist/py.typed
pyanilist-0.9.0.dist-info/METADATA
pyanilist-0.9.0.dist-info/WHEEL
pyanilist-0.9.0.dist-info/licenses/LICENSE
pyanilist-0.9.0.dist-info/RECORD
