Metadata-Version: 2.4
Name: pyanilist
Version: 0.9.0
Summary: A Python wrapper for the AniList API.
Project-URL: Documentation, https://ravencentric.cc/pyanilist/
Project-URL: Repository, https://github.com/Ravencentric/pyanilist
Author-email: Ravencentric <me@ravencentric.cc>
License-Expression: MIT
License-File: LICENSE
Keywords: anilist,anime,async
Classifier: Operating System :: OS Independent
Classifier: Programming Language :: Python :: 3.10
Classifier: Programming Language :: Python :: 3.11
Classifier: Programming Language :: Python :: 3.12
Classifier: Programming Language :: Python :: 3.13
Classifier: Typing :: Typed
Requires-Python: >=3.10
Requires-Dist: httpx>=0.27.2
Requires-Dist: msgspec>=0.19.0
